generator/__init__.py
generator/base.py
generator/behave_gen.py
generator/playwright_gen.py
generator/pytest_gen.py
generator/robot_gen.py
letgen-0.1.1.dist-info/METADATA
letgen-0.1.1.dist-info/WHEEL
letgen-0.1.1.dist-info/entry_points.txt
letgen-0.1.1.dist-info/top_level.txt
letgen-0.1.1.dist-info/RECORD
