Metadata-Version: 2.4
Name: letgen
Version: 0.1.1
Summary: Gere testes automatizados em Python usando IA e linguagem natural
Home-page: https://github.com/CarlossViniciuss/let
Author: Carlos Vinicius
Classifier: Programming Language :: Python :: 3
Classifier: License :: OSI Approved :: MIT License
Classifier: Operating System :: OS Independent
Classifier: Topic :: Software Development :: Testing
Classifier: Intended Audience :: Developers
Requires-Python: >=3.7
Requires-Dist: click
Requires-Dist: rich
Requires-Dist: requests
Dynamic: author
Dynamic: classifier
Dynamic: description
Dynamic: description-content-type
Dynamic: home-page
Dynamic: requires-dist
Dynamic: requires-python
Dynamic: summary
